{
	"format_version": "1.21.6",
	"credit": "Created by Maltsburg",
	"textures": {
		"material": "block/oak_planks",
		"particle": "#material"
	},
	"elements": [
		{
			"from": [4.5, 4, 5.25],
			"to": [11.5, 4.6, 11.75],
			"rotation": {"angle": 0, "axis": "y", "origin": [8, 4.25, 7.575]},
			"faces": {
				"north": {"uv": [0, 15, 16, 16], "texture": "#material"},
				"east": {"uv": [0, 2, 1, 16], "rotation": 90, "texture": "#material"},
				"south": {"uv": [0, 15, 16, 16], "texture": "#material"},
				"west": {"uv": [15, 2, 16, 16], "rotation": 270, "texture": "#material"},
				"up": {"uv": [0, 2, 16, 16], "texture": "#material"},
				"down": {"uv": [0, 2, 16, 16], "rotation": 180, "texture": "#material"}
			}
		},
		{
			"from": [4.5, 4, 4.25],
			"to": [11.5, 4.6, 4.75],
			"rotation": {"angle": 0, "axis": "y", "origin": [8, 4.25, 7.575]},
			"faces": {
				"north": {"uv": [0, 15, 16, 16], "texture": "#material"},
				"east": {"uv": [0, 0, 1, 0.9], "texture": "#material"},
				"south": {"uv": [0, 0, 16, 1], "texture": "#material"},
				"west": {"uv": [15, 0, 16, 1], "rotation": 90, "texture": "#material"},
				"up": {"uv": [0, 0, 16, 1], "rotation": 180, "texture": "#material"},
				"down": {"uv": [0, 0, 16, 1], "rotation": 180, "texture": "#material"}
			}
		},
		{
			"from": [8.9, 4, 4.75],
			"to": [11.5, 4.6, 5.25],
			"rotation": {"angle": 0, "axis": "y", "origin": [8, 4.25, 7.575]},
			"faces": {
				"north": {"uv": [0, 0, 16, 16], "texture": "#material"},
				"east": {"uv": [0, 1, 1, 1.9], "rotation": 90, "texture": "#material"},
				"south": {"uv": [0, 0, 16, 16], "texture": "#material"},
				"west": {"uv": [0, 0, 1, 1], "texture": "#material"},
				"up": {"uv": [10, 1, 16, 2], "rotation": 180, "texture": "#material"},
				"down": {"uv": [0, 1, 6, 2], "rotation": 180, "texture": "#material"}
			}
		},
		{
			"from": [4.5, 4, 4.75],
			"to": [7.1, 4.6, 5.25],
			"rotation": {"angle": 0, "axis": "y", "origin": [8, 4.25, 7.575]},
			"faces": {
				"north": {"uv": [0, 0, 16, 16], "texture": "#material"},
				"east": {"uv": [15, 15, 16, 16], "texture": "#material"},
				"south": {"uv": [0, 0, 16, 16], "texture": "#material"},
				"west": {"uv": [15, 1, 16, 2], "rotation": 90, "texture": "#material"},
				"up": {"uv": [0, 1, 6, 2], "rotation": 180, "texture": "#material"},
				"down": {"uv": [10, 1, 16, 2], "rotation": 180, "texture": "#material"}
			}
		}
	],
	"gui_light": "front",
	"display": {
		"thirdperson_righthand": {
			"rotation": [79.08, -0.07, 11.61],
			"translation": [0, 2.75, 2.25],
			"scale": [0.75, 0.75, 0.75]
		},
		"thirdperson_lefthand": {
			"rotation": [79.08, -0.07, 11.61],
			"translation": [0, 2.75, 2.25],
			"scale": [0.75, 0.75, 0.75]
		},
		"firstperson_righthand": {
			"rotation": [42.24, 1.33, 34.33],
			"translation": [2, 4.5, 0.75]
		},
		"firstperson_lefthand": {
			"rotation": [42.24, 1.33, 34.33],
			"translation": [2, 4.5, 0.75]
		},
		"ground": {
			"translation": [0, 1, 0],
			"scale": [0.75, 0.75, 0.75]
		},
		"gui": {
			"rotation": [90, 0, 0],
			"translation": [0, 0, 7],
			"scale": [2, 2, 2]
		},
		"head": {
			"scale": [2, 2, 2]
		},
		"on_shelf": {
			"rotation": [90, 0, 0],
			"translation": [0, 0, 7],
			"scale": [2, 2, 2]
		}
	}
}